ksycopg2/__init__.py
ksycopg2/_ipaddress.py
ksycopg2/_json.py
ksycopg2/_ksycopg.cpython-36m-x86_64-linux-gnu.so
ksycopg2/_lru_cache.py
ksycopg2/_range.py
ksycopg2/compat.py
ksycopg2/errorcodes.py
ksycopg2/errors.py
ksycopg2/extensions.py
ksycopg2/extras.py
ksycopg2/libkci.so.5
ksycopg2/pool.py
ksycopg2/sql.py
ksycopg2/tz.py
test_ksy-2.8.5.data/data/libkci.so.5
test_ksy-2.8.5.dist-info/METADATA
test_ksy-2.8.5.dist-info/WHEEL
test_ksy-2.8.5.dist-info/top_level.txt
test_ksy-2.8.5.dist-info/RECORD
